mitbih_processor/__init__.py
mitbih_processor/__main__.py
mitbih_processor/config.py
mitbih_processor/datasets.py
mitbih_processor/describer.py
mitbih_processor/preprocessing.py
mitbih_processor/qrsintervals.py
webclient/__init__.py
webclient/arrcls.py
webclient/static/css/bootstrap.min.css
webclient/static/js/Chart.min.js
webclient/static/js/bootstrap.bundle.min.js
webclient/static/js/feature_extraction.js
webclient/static/js/get_classifier.js
webclient/static/js/jquery-3.5.1.slim.min.js
webclient/static/js/signal_analyzer.js
webclient/static/js/signal_analyzer_report.js
webclient/static/js/signal_extraction.js
webclient/templates/base.html
webclient/templates/arrcls/feature_extraction.html
webclient/templates/arrcls/get_classifier.html
webclient/templates/arrcls/get_classifier_report.html
webclient/templates/arrcls/signal_analyzer.html
webclient/templates/arrcls/signal_analyzer_report.html
webclient/templates/arrcls/signal_extraction.html
webclient/templates/arrcls/signal_extraction_report.html
mitbih_processor-1.0.4.dist-info/METADATA
mitbih_processor-1.0.4.dist-info/WHEEL
mitbih_processor-1.0.4.dist-info/entry_points.txt
mitbih_processor-1.0.4.dist-info/top_level.txt
mitbih_processor-1.0.4.dist-info/RECORD
